maraudersmap/__init__.py
maraudersmap/callgraph.py
maraudersmap/cli.py
maraudersmap/colors_utils.py
maraudersmap/fortran_rc_default.yml
maraudersmap/full_graph_actions.py
maraudersmap/git_patches.py
maraudersmap/grep.py
maraudersmap/imports.py
maraudersmap/layout_debug.py
maraudersmap/layout_forces.py
maraudersmap/layout_misc.py
maraudersmap/layout_ripple.py
maraudersmap/macro_tree.py
maraudersmap/mmap_in.yml
maraudersmap/mmap_startlog.py
maraudersmap/nx_utils.py
maraudersmap/python_rc_default.yml
maraudersmap/quadtree.py
maraudersmap/scatter.py
maraudersmap/score.py
maraudersmap/show_graphviz.py
maraudersmap/show_nobvisual.py
maraudersmap/show_plotly.py
maraudersmap/show_pyplot.py
maraudersmap/show_pyplot_interactive.py
maraudersmap/show_pyvis.py
maraudersmap/show_tree_js.py
maraudersmap/show_tree_nob.py
maraudersmap/stats_mvp.py
maraudersmap/valgrindload.py
maraudersmap-0.8.0.dist-info/licenses/LICENSE.txt
maraudersmap-0.8.0.dist-info/METADATA
maraudersmap-0.8.0.dist-info/WHEEL
maraudersmap-0.8.0.dist-info/entry_points.txt
maraudersmap-0.8.0.dist-info/top_level.txt
maraudersmap-0.8.0.dist-info/RECORD
