Metadata-Version: 2.4
Name: maraudersmap
Version: 0.8.0
Summary: Fast generation of Inports graph
Home-page: https://gitlab.com/cerfacs/maraudersmap
Author: CoopTeam-CERFACS
Author-email: coop@cerfacs.com
Project-URL: Homepage, https://gitlab.com/cerfacs/maraudersmap
Project-URL: Documentation, https://maraudersmap.readthedocs.io/en/latest/
Project-URL: Bug Tracker, https://gitlab.com/cerfacs/maraudersmap/-/issues
Keywords: findimports graph
Classifier: Programming Language :: Python :: 3.7
Classifier: Programming Language :: Python :: 3.8
Classifier: Programming Language :: Python :: 3.9
Classifier: Programming Language :: Python :: 3.10
Classifier: License :: OSI Approved :: MIT License
Requires-Python: >=3.7
License-File: LICENSE.txt
Requires-Dist: click
Requires-Dist: pyyaml
Requires-Dist: tucan>=0.4.4
Requires-Dist: nobvisual>=1.0.0
Requires-Dist: loguru
Requires-Dist: networkx
Requires-Dist: pyvis
Requires-Dist: graphviz
Requires-Dist: regex
Requires-Dist: numpy
Requires-Dist: matplotlib
Requires-Dist: scipy
Requires-Dist: nob
Requires-Dist: tol-colors
Requires-Dist: dash
Requires-Dist: dash_bootstrap_components
Requires-Dist: dash_daq
Requires-Dist: kaleido
Requires-Dist: typing-extensions>=4.13.2
Requires-Dist: moonframe
Provides-Extra: tests
Requires-Dist: pytest; extra == "tests"
Requires-Dist: pytest-coverage; extra == "tests"
Requires-Dist: pytest-allclose; extra == "tests"
Requires-Dist: pytest-benchmark; extra == "tests"
Provides-Extra: docs
Requires-Dist: sphinx_rtd_theme; extra == "docs"
Requires-Dist: recommonmark; extra == "docs"
Dynamic: license-file
